{
  "metadata": {
    "default_station": "9414290",
    "default_tide_height": 2
  },
  "tides": [
    {
      "t": "2020-12-09 00:00",
      "v": "3.970"
    },
    {
      "t": "2020-12-09 05:18",
      "v": "1.961"
    },
    {
      "t": "2020-12-09 10:18",
      "v": "2.077"
    },
    {
      "t": "2020-12-09 19:36",
      "v": "1.950"
    },
    {
      "t": "2020-12-09 22:48",
      "v": "2.035"
    },
    {
      "t": "2020-12-10 06:42",
      "v": "1.955"
    },
    {
      "t": "2020-12-10 10:42",
      "v": "2.070"
    },
    {
      "t": "2020-12-10 19:48",
      "v": "1.910"
    },
    {
      "t": "2020-12-11 00:36",
      "v": "2.040"
    },
    {
      "t": "2020-12-11 08:12",
      "v": "1.939"
    },
    {
      "t": "2020-12-11 11:00",
      "v": "2.063"
    },
    {
      "t": "2020-12-11 20:12",
      "v": "1.973"
    },
    {
      "t": "2020-12-12 02:00",
      "v": "2.065"
    },
    {
      "t": "2020-12-12 09:48",
      "v": "1.997"
    },
    {
      "t": "2020-12-12 11:00",
      "v": "2.022"
    },
    {
      "t": "2020-12-12 20:48",
      "v": "1.932"
    },
    {
      "t": "2020-12-13 03:06",
      "v": "2.024"
    },
    {
      "t": "2020-12-13 21:30",
      "v": "1.837"
    },
    {
      "t": "2020-12-14 04:06",
      "v": "2.040"
    },
    {
      "t": "2020-12-14 22:12",
      "v": "1.848"
    },
    {
      "t": "2020-12-15 05:00",
      "v": "2.056"
    },
    {
      "t": "2020-12-15 22:54",
      "v": "1.944"
    },
    {
      "t": "2020-12-16 05:48",
      "v": "2.034"
    },
    {
      "t": "2020-12-16 23:42",
      "v": "1.903"
    }
  ]
}