{
  "units": "feet",
  "HarmonicConstituents": [
    {
      "number": 1,
      "name": "M2",
      "description": "Principal lunar semidiurnal constituent",
      "amplitude": 0.95,
      "phase_GMT": 15.0,
      "phase_local": 143.1,
      "speed": 28.984104,
      "comments": "Vector Averaged of 3 months (1-3/2015).  Long period constituents from 9415144 Port Chicago."
    },
    {
      "number": 2,
      "name": "S2",
      "description": "Principal solar semidiurnal constituent",
      "amplitude": 0.17,
      "phase_GMT": 31.9,
      "phase_local": 151.9,
      "speed": 30.0,
      "comments": "Vector Averaged of 3 months (1-3/2015).  Long period constituents from 9415144 Port Chicago."
    },
    {
      "number": 3,
      "name": "N2",
      "description": "Larger lunar elliptic semidiurnal constituent",
      "amplitude": 0.17,
      "phase_GMT": 356.7,
      "phase_local": 129.2,
      "speed": 28.43973,
      "comments": "Vector Averaged of 3 months (1-3/2015).  Long period constituents from 9415144 Port Chicago."
    },
    {
      "number": 4,
      "name": "K1",
      "description": "Lunar diurnal constituent",
      "amplitude": 0.63,
      "phase_GMT": 323.5,
      "phase_local": 203.2,
      "speed": 15.041069,
      "comments": "Vector Averaged of 3 months (1-3/2015).  Long period constituents from 9415144 Port Chicago."
    },
    {
      "number": 5,
      "name": "M4",
      "description": "Shallow water overtides of principal lunar constituent",
      "amplitude": 0.02,
      "phase_GMT": 267.9,
      "phase_local": 164.2,
      "speed": 57.96821,
      "comments": "Vector Averaged of 3 months (1-3/2015).  Long period constituents from 9415144 Port Chicago."
    },
    {
      "number": 6,
      "name": "O1",
      "description": "Lunar diurnal constituent",
      "amplitude": 0.42,
      "phase_GMT": 317.8,
      "phase_local": 206.2,
      "speed": 13.943035,
      "comments": "Vector Averaged of 3 months (1-3/2015).  Long period constituents from 9415144 Port Chicago."
    },
    {
      "number": 7,
      "name": "M6",
      "description": "Shallow water overtides of principal lunar constituent",
      "amplitude": 0.03,
      "phase_GMT": 52.2,
      "phase_local": 76.6,
      "speed": 86.95232,
      "comments": "Vector Averaged of 3 months (1-3/2015).  Long period constituents from 9415144 Port Chicago."
    },
    {
      "number": 8,
      "name": "MK3",
      "description": "Shallow water terdiurnal",
      "amplitude": 0.0,
      "phase_GMT": 0.0,
      "phase_local": 0.0,
      "speed": 44.025173,
      "comments": "Vector Averaged of 3 months (1-3/2015).  Long period constituents from 9415144 Port Chicago."
    },
    {
      "number": 9,
      "name": "S4",
      "description": "Shallow water overtides of principal solar constituent",
      "amplitude": 0.0,
      "phase_GMT": 354.4,
      "phase_local": 234.4,
      "speed": 60.0,
      "comments": "Vector Averaged of 3 months (1-3/2015).  Long period constituents from 9415144 Port Chicago."
    },
    {
      "number": 10,
      "name": "MN4",
      "description": "Shallow water quarter diurnal constituent",
      "amplitude": 0.0,
      "phase_GMT": 0.0,
      "phase_local": 0.0,
      "speed": 57.423832,
      "comments": "Vector Averaged of 3 months (1-3/2015).  Long period constituents from 9415144 Port Chicago."
    },
    {
      "number": 11,
      "name": "NU2",
      "description": "Larger lunar evectional constituent",
      "amplitude": 0.03,
      "phase_GMT": 359.1,
      "phase_local": 131.0,
      "speed": 28.512583,
      "comments": "Vector Averaged of 3 months (1-3/2015).  Long period constituents from 9415144 Port Chicago."
    },
    {
      "number": 12,
      "name": "S6",
      "description": "Shallow water overtides of principal solar constituent",
      "amplitude": 0.0,
      "phase_GMT": 0.0,
      "phase_local": 0.0,
      "speed": 90.0,
      "comments": "Vector Averaged of 3 months (1-3/2015).  Long period constituents from 9415144 Port Chicago."
    },
    {
      "number": 13,
      "name": "MU2",
      "description": "Variational constituent",
      "amplitude": 0.02,
      "phase_GMT": 357.7,
      "phase_local": 134.0,
      "speed": 27.968208,
      "comments": "Vector Averaged of 3 months (1-3/2015).  Long period constituents from 9415144 Port Chicago."
    },
    {
      "number": 14,
      "name": "2N2",
      "description": "Lunar elliptical semidiurnal second-order constituent",
      "amplitude": 0.02,
      "phase_GMT": 338.4,
      "phase_local": 115.2,
      "speed": 27.895355,
      "comments": "Vector Averaged of 3 months (1-3/2015).  Long period constituents from 9415144 Port Chicago."
    },
    {
      "number": 15,
      "name": "OO1",
      "description": "Lunar diurnal",
      "amplitude": 0.02,
      "phase_GMT": 329.2,
      "phase_local": 200.1,
      "speed": 16.139101,
      "comments": "Vector Averaged of 3 months (1-3/2015).  Long period constituents from 9415144 Port Chicago."
    },
    {
      "number": 16,
      "name": "LAM2",
      "description": "Smaller lunar evectional constituent",
      "amplitude": 0.01,
      "phase_GMT": 23.0,
      "phase_local": 147.3,
      "speed": 29.455626,
      "comments": "Vector Averaged of 3 months (1-3/2015).  Long period constituents from 9415144 Port Chicago."
    },
    {
      "number": 17,
      "name": "S1",
      "description": "Solar diurnal constituent",
      "amplitude": 0.0,
      "phase_GMT": 0.0,
      "phase_local": 0.0,
      "speed": 15.0,
      "comments": "Vector Averaged of 3 months (1-3/2015).  Long period constituents from 9415144 Port Chicago."
    },
    {
      "number": 18,
      "name": "M1",
      "description": "Smaller lunar elliptic diurnal constituent",
      "amplitude": 0.03,
      "phase_GMT": 320.8,
      "phase_local": 204.8,
      "speed": 14.496694,
      "comments": "Vector Averaged of 3 months (1-3/2015).  Long period constituents from 9415144 Port Chicago."
    },
    {
      "number": 19,
      "name": "J1",
      "description": "Smaller lunar elliptic diurnal constituent",
      "amplitude": 0.03,
      "phase_GMT": 326.1,
      "phase_local": 201.5,
      "speed": 15.5854435,
      "comments": "Vector Averaged of 3 months (1-3/2015).  Long period constituents from 9415144 Port Chicago."
    },
    {
      "number": 20,
      "name": "MM",
      "description": "Lunar monthly constituent",
      "amplitude": 0.05,
      "phase_GMT": 34.4,
      "phase_local": 30.0,
      "speed": 0.5443747,
      "comments": "Vector Averaged of 3 months (1-3/2015).  Long period constituents from 9415144 Port Chicago."
    },
    {
      "number": 21,
      "name": "SSA",
      "description": "Solar semiannual constituent",
      "amplitude": 0.14,
      "phase_GMT": 264.8,
      "phase_local": 264.1,
      "speed": 0.0821373,
      "comments": "Vector Averaged of 3 months (1-3/2015).  Long period constituents from 9415144 Port Chicago."
    },
    {
      "number": 22,
      "name": "SA",
      "description": "Solar annual constituent",
      "amplitude": 0.09,
      "phase_GMT": 144.6,
      "phase_local": 144.3,
      "speed": 0.0410686,
      "comments": "Vector Averaged of 3 months (1-3/2015).  Long period constituents from 9415144 Port Chicago."
    },
    {
      "number": 23,
      "name": "MSF",
      "description": "Lunisolar synodic fortnightly constituent",
      "amplitude": 0.1,
      "phase_GMT": 18.1,
      "phase_local": 10.0,
      "speed": 1.0158958,
      "comments": "Vector Averaged of 3 months (1-3/2015).  Long period constituents from 9415144 Port Chicago."
    },
    {
      "number": 24,
      "name": "MF",
      "description": "Lunisolar fortnightly constituent",
      "amplitude": 0.13,
      "phase_GMT": 184.3,
      "phase_local": 175.5,
      "speed": 1.0980331,
      "comments": "Vector Averaged of 3 months (1-3/2015).  Long period constituents from 9415144 Port Chicago."
    },
    {
      "number": 25,
      "name": "RHO",
      "description": "Larger lunar evectional diurnal constituent",
      "amplitude": 0.02,
      "phase_GMT": 315.5,
      "phase_local": 207.7,
      "speed": 13.471515,
      "comments": "Vector Averaged of 3 months (1-3/2015).  Long period constituents from 9415144 Port Chicago."
    },
    {
      "number": 26,
      "name": "Q1",
      "description": "Larger lunar elliptic diurnal constituent",
      "amplitude": 0.08,
      "phase_GMT": 315.1,
      "phase_local": 207.9,
      "speed": 13.398661,
      "comments": "Vector Averaged of 3 months (1-3/2015).  Long period constituents from 9415144 Port Chicago."
    },
    {
      "number": 27,
      "name": "T2",
      "description": "Larger solar elliptic constituent",
      "amplitude": 0.01,
      "phase_GMT": 31.5,
      "phase_local": 151.8,
      "speed": 29.958933,
      "comments": "Vector Averaged of 3 months (1-3/2015).  Long period constituents from 9415144 Port Chicago."
    },
    {
      "number": 28,
      "name": "R2",
      "description": "Smaller solar elliptic constituent",
      "amplitude": 0.0,
      "phase_GMT": 0.0,
      "phase_local": 0.0,
      "speed": 30.041067,
      "comments": "Vector Averaged of 3 months (1-3/2015).  Long period constituents from 9415144 Port Chicago."
    },
    {
      "number": 29,
      "name": "2Q1",
      "description": "Larger elliptic diurnal",
      "amplitude": 0.01,
      "phase_GMT": 313.4,
      "phase_local": 210.6,
      "speed": 12.854286,
      "comments": "Vector Averaged of 3 months (1-3/2015).  Long period constituents from 9415144 Port Chicago."
    },
    {
      "number": 30,
      "name": "P1",
      "description": "Solar diurnal constituent",
      "amplitude": 0.21,
      "phase_GMT": 323.0,
      "phase_local": 203.4,
      "speed": 14.958931,
      "comments": "Vector Averaged of 3 months (1-3/2015).  Long period constituents from 9415144 Port Chicago."
    },
    {
      "number": 31,
      "name": "2SM2",
      "description": "Shallow water semidiurnal constituent",
      "amplitude": 0.0,
      "phase_GMT": 0.0,
      "phase_local": 0.0,
      "speed": 31.015896,
      "comments": "Vector Averaged of 3 months (1-3/2015).  Long period constituents from 9415144 Port Chicago."
    },
    {
      "number": 32,
      "name": "M3",
      "description": "Lunar terdiurnal constituent",
      "amplitude": 0.0,
      "phase_GMT": 0.0,
      "phase_local": 0.0,
      "speed": 43.47616,
      "comments": "Vector Averaged of 3 months (1-3/2015).  Long period constituents from 9415144 Port Chicago."
    },
    {
      "number": 33,
      "name": "L2",
      "description": "Smaller lunar elliptic semidiurnal constituent",
      "amplitude": 0.03,
      "phase_GMT": 33.3,
      "phase_local": 157.0,
      "speed": 29.528479,
      "comments": "Vector Averaged of 3 months (1-3/2015).  Long period constituents from 9415144 Port Chicago."
    },
    {
      "number": 34,
      "name": "2MK3",
      "description": "Shallow water terdiurnal constituent",
      "amplitude": 0.0,
      "phase_GMT": 0.0,
      "phase_local": 0.0,
      "speed": 42.92714,
      "comments": "Vector Averaged of 3 months (1-3/2015).  Long period constituents from 9415144 Port Chicago."
    },
    {
      "number": 35,
      "name": "K2",
      "description": "Lunisolar semidiurnal constituent",
      "amplitude": 0.05,
      "phase_GMT": 33.2,
      "phase_local": 152.6,
      "speed": 30.082138,
      "comments": "Vector Averaged of 3 months (1-3/2015).  Long period constituents from 9415144 Port Chicago."
    },
    {
      "number": 36,
      "name": "M8",
      "description": "Shallow water eighth diurnal constituent",
      "amplitude": 0.0,
      "phase_GMT": 337.6,
      "phase_local": 130.1,
      "speed": 115.93642,
      "comments": "Vector Averaged of 3 months (1-3/2015).  Long period constituents from 9415144 Port Chicago."
    },
    {
      "number": 37,
      "name": "MS4",
      "description": "Shallow water quarter diurnal constituent",
      "amplitude": 0.0,
      "phase_GMT": 0.0,
      "phase_local": 0.0,
      "speed": 58.984104,
      "comments": "Vector Averaged of 3 months (1-3/2015).  Long period constituents from 9415144 Port Chicago."
    }
  ],
  "self": "https://api.tidesandcurrents.noaa.gov/mdapi/prod/webapi/stations/9415229/harcon.json"
}