{
  "units": "feet",
  "HarmonicConstituents": [
    {
      "number": 1,
      "name": "M2",
      "description": "Principal lunar semidiurnal constituent",
      "amplitude": 2.39,
      "phase_GMT": 220.2,
      "phase_local": 348.4,
      "speed": 28.984104,
      "comments": "Average of three (3) 29-day harmonic analyses.  Sa, Ssa, and Mf from 9418767 North Spit, Humboldt Bay."
    },
    {
      "number": 2,
      "name": "S2",
      "description": "Principal solar semidiurnal constituent",
      "amplitude": 0.63,
      "phase_GMT": 243.7,
      "phase_local": 3.7,
      "speed": 30.0,
      "comments": "Average of three (3) 29-day harmonic analyses.  Sa, Ssa, and Mf from 9418767 North Spit, Humboldt Bay."
    },
    {
      "number": 3,
      "name": "N2",
      "description": "Larger lunar elliptic semidiurnal constituent",
      "amplitude": 0.5,
      "phase_GMT": 198.5,
      "phase_local": 330.9,
      "speed": 28.43973,
      "comments": "Average of three (3) 29-day harmonic analyses.  Sa, Ssa, and Mf from 9418767 North Spit, Humboldt Bay."
    },
    {
      "number": 4,
      "name": "K1",
      "description": "Lunar diurnal constituent",
      "amplitude": 1.34,
      "phase_GMT": 235.0,
      "phase_local": 114.7,
      "speed": 15.041069,
      "comments": "Average of three (3) 29-day harmonic analyses.  Sa, Ssa, and Mf from 9418767 North Spit, Humboldt Bay."
    },
    {
      "number": 5,
      "name": "M4",
      "description": "Shallow water overtides of principal lunar constituent",
      "amplitude": 0.09,
      "phase_GMT": 202.6,
      "phase_local": 98.8,
      "speed": 57.96821,
      "comments": "Average of three (3) 29-day harmonic analyses.  Sa, Ssa, and Mf from 9418767 North Spit, Humboldt Bay."
    },
    {
      "number": 6,
      "name": "O1",
      "description": "Lunar diurnal constituent",
      "amplitude": 0.79,
      "phase_GMT": 221.0,
      "phase_local": 109.5,
      "speed": 13.943035,
      "comments": "Average of three (3) 29-day harmonic analyses.  Sa, Ssa, and Mf from 9418767 North Spit, Humboldt Bay."
    },
    {
      "number": 7,
      "name": "M6",
      "description": "Shallow water overtides of principal lunar constituent",
      "amplitude": 0.07,
      "phase_GMT": 294.2,
      "phase_local": 318.6,
      "speed": 86.95232,
      "comments": "Average of three (3) 29-day harmonic analyses.  Sa, Ssa, and Mf from 9418767 North Spit, Humboldt Bay."
    },
    {
      "number": 8,
      "name": "MK3",
      "description": "Shallow water terdiurnal",
      "amplitude": 0.0,
      "phase_GMT": 0.0,
      "phase_local": 0.0,
      "speed": 44.025173,
      "comments": "Average of three (3) 29-day harmonic analyses.  Sa, Ssa, and Mf from 9418767 North Spit, Humboldt Bay."
    },
    {
      "number": 9,
      "name": "S4",
      "description": "Shallow water overtides of principal solar constituent",
      "amplitude": 0.01,
      "phase_GMT": 31.9,
      "phase_local": 271.9,
      "speed": 60.0,
      "comments": "Average of three (3) 29-day harmonic analyses.  Sa, Ssa, and Mf from 9418767 North Spit, Humboldt Bay."
    },
    {
      "number": 10,
      "name": "MN4",
      "description": "Shallow water quarter diurnal constituent",
      "amplitude": 0.0,
      "phase_GMT": 0.0,
      "phase_local": 0.0,
      "speed": 57.423832,
      "comments": "Average of three (3) 29-day harmonic analyses.  Sa, Ssa, and Mf from 9418767 North Spit, Humboldt Bay."
    },
    {
      "number": 11,
      "name": "NU2",
      "description": "Larger lunar evectional constituent",
      "amplitude": 0.1,
      "phase_GMT": 201.3,
      "phase_local": 333.2,
      "speed": 28.512583,
      "comments": "Average of three (3) 29-day harmonic analyses.  Sa, Ssa, and Mf from 9418767 North Spit, Humboldt Bay."
    },
    {
      "number": 12,
      "name": "S6",
      "description": "Shallow water overtides of principal solar constituent",
      "amplitude": 0.01,
      "phase_GMT": 181.0,
      "phase_local": 181.0,
      "speed": 90.0,
      "comments": "Average of three (3) 29-day harmonic analyses.  Sa, Ssa, and Mf from 9418767 North Spit, Humboldt Bay."
    },
    {
      "number": 13,
      "name": "MU2",
      "description": "Variational constituent",
      "amplitude": 0.06,
      "phase_GMT": 196.8,
      "phase_local": 333.0,
      "speed": 27.968208,
      "comments": "Average of three (3) 29-day harmonic analyses.  Sa, Ssa, and Mf from 9418767 North Spit, Humboldt Bay."
    },
    {
      "number": 14,
      "name": "2N2",
      "description": "Lunar elliptical semidiurnal second-order constituent",
      "amplitude": 0.07,
      "phase_GMT": 176.6,
      "phase_local": 313.5,
      "speed": 27.895355,
      "comments": "Average of three (3) 29-day harmonic analyses.  Sa, Ssa, and Mf from 9418767 North Spit, Humboldt Bay."
    },
    {
      "number": 15,
      "name": "OO1",
      "description": "Lunar diurnal",
      "amplitude": 0.03,
      "phase_GMT": 249.1,
      "phase_local": 120.0,
      "speed": 16.139101,
      "comments": "Average of three (3) 29-day harmonic analyses.  Sa, Ssa, and Mf from 9418767 North Spit, Humboldt Bay."
    },
    {
      "number": 16,
      "name": "LAM2",
      "description": "Smaller lunar evectional constituent",
      "amplitude": 0.02,
      "phase_GMT": 231.1,
      "phase_local": 355.5,
      "speed": 29.455626,
      "comments": "Average of three (3) 29-day harmonic analyses.  Sa, Ssa, and Mf from 9418767 North Spit, Humboldt Bay."
    },
    {
      "number": 17,
      "name": "S1",
      "description": "Solar diurnal constituent",
      "amplitude": 0.0,
      "phase_GMT": 0.0,
      "phase_local": 0.0,
      "speed": 15.0,
      "comments": "Average of three (3) 29-day harmonic analyses.  Sa, Ssa, and Mf from 9418767 North Spit, Humboldt Bay."
    },
    {
      "number": 18,
      "name": "M1",
      "description": "Smaller lunar elliptic diurnal constituent",
      "amplitude": 0.06,
      "phase_GMT": 228.1,
      "phase_local": 112.1,
      "speed": 14.496694,
      "comments": "Average of three (3) 29-day harmonic analyses.  Sa, Ssa, and Mf from 9418767 North Spit, Humboldt Bay."
    },
    {
      "number": 19,
      "name": "J1",
      "description": "Smaller lunar elliptic diurnal constituent",
      "amplitude": 0.06,
      "phase_GMT": 242.0,
      "phase_local": 117.3,
      "speed": 15.5854435,
      "comments": "Average of three (3) 29-day harmonic analyses.  Sa, Ssa, and Mf from 9418767 North Spit, Humboldt Bay."
    },
    {
      "number": 20,
      "name": "MM",
      "description": "Lunar monthly constituent",
      "amplitude": 0.0,
      "phase_GMT": 0.0,
      "phase_local": 0.0,
      "speed": 0.5443747,
      "comments": "Average of three (3) 29-day harmonic analyses.  Sa, Ssa, and Mf from 9418767 North Spit, Humboldt Bay."
    },
    {
      "number": 21,
      "name": "SSA",
      "description": "Solar semiannual constituent",
      "amplitude": 0.12,
      "phase_GMT": 264.1,
      "phase_local": 263.4,
      "speed": 0.0821373,
      "comments": "Average of three (3) 29-day harmonic analyses.  Sa, Ssa, and Mf from 9418767 North Spit, Humboldt Bay."
    },
    {
      "number": 22,
      "name": "SA",
      "description": "Solar annual constituent",
      "amplitude": 0.21,
      "phase_GMT": 255.0,
      "phase_local": 254.7,
      "speed": 0.0410686,
      "comments": "Average of three (3) 29-day harmonic analyses.  Sa, Ssa, and Mf from 9418767 North Spit, Humboldt Bay."
    },
    {
      "number": 23,
      "name": "MSF",
      "description": "Lunisolar synodic fortnightly constituent",
      "amplitude": 0.0,
      "phase_GMT": 0.0,
      "phase_local": 0.0,
      "speed": 1.0158958,
      "comments": "Average of three (3) 29-day harmonic analyses.  Sa, Ssa, and Mf from 9418767 North Spit, Humboldt Bay."
    },
    {
      "number": 24,
      "name": "MF",
      "description": "Lunisolar fortnightly constituent",
      "amplitude": 0.05,
      "phase_GMT": 149.0,
      "phase_local": 140.2,
      "speed": 1.0980331,
      "comments": "Average of three (3) 29-day harmonic analyses.  Sa, Ssa, and Mf from 9418767 North Spit, Humboldt Bay."
    },
    {
      "number": 25,
      "name": "RHO",
      "description": "Larger lunar evectional diurnal constituent",
      "amplitude": 0.03,
      "phase_GMT": 215.0,
      "phase_local": 107.2,
      "speed": 13.471515,
      "comments": "Average of three (3) 29-day harmonic analyses.  Sa, Ssa, and Mf from 9418767 North Spit, Humboldt Bay."
    },
    {
      "number": 26,
      "name": "Q1",
      "description": "Larger lunar elliptic diurnal constituent",
      "amplitude": 0.15,
      "phase_GMT": 214.0,
      "phase_local": 106.8,
      "speed": 13.398661,
      "comments": "Average of three (3) 29-day harmonic analyses.  Sa, Ssa, and Mf from 9418767 North Spit, Humboldt Bay."
    },
    {
      "number": 27,
      "name": "T2",
      "description": "Larger solar elliptic constituent",
      "amplitude": 0.04,
      "phase_GMT": 242.8,
      "phase_local": 3.1,
      "speed": 29.958933,
      "comments": "Average of three (3) 29-day harmonic analyses.  Sa, Ssa, and Mf from 9418767 North Spit, Humboldt Bay."
    },
    {
      "number": 28,
      "name": "R2",
      "description": "Smaller solar elliptic constituent",
      "amplitude": 0.01,
      "phase_GMT": 244.3,
      "phase_local": 4.0,
      "speed": 30.041067,
      "comments": "Average of three (3) 29-day harmonic analyses.  Sa, Ssa, and Mf from 9418767 North Spit, Humboldt Bay."
    },
    {
      "number": 29,
      "name": "2Q1",
      "description": "Larger elliptic diurnal",
      "amplitude": 0.02,
      "phase_GMT": 207.1,
      "phase_local": 104.2,
      "speed": 12.854286,
      "comments": "Average of three (3) 29-day harmonic analyses.  Sa, Ssa, and Mf from 9418767 North Spit, Humboldt Bay."
    },
    {
      "number": 30,
      "name": "P1",
      "description": "Solar diurnal constituent",
      "amplitude": 0.44,
      "phase_GMT": 234.0,
      "phase_local": 114.4,
      "speed": 14.958931,
      "comments": "Average of three (3) 29-day harmonic analyses.  Sa, Ssa, and Mf from 9418767 North Spit, Humboldt Bay."
    },
    {
      "number": 31,
      "name": "2SM2",
      "description": "Shallow water semidiurnal constituent",
      "amplitude": 0.0,
      "phase_GMT": 0.0,
      "phase_local": 0.0,
      "speed": 31.015896,
      "comments": "Average of three (3) 29-day harmonic analyses.  Sa, Ssa, and Mf from 9418767 North Spit, Humboldt Bay."
    },
    {
      "number": 32,
      "name": "M3",
      "description": "Lunar terdiurnal constituent",
      "amplitude": 0.0,
      "phase_GMT": 0.0,
      "phase_local": 0.0,
      "speed": 43.47616,
      "comments": "Average of three (3) 29-day harmonic analyses.  Sa, Ssa, and Mf from 9418767 North Spit, Humboldt Bay."
    },
    {
      "number": 33,
      "name": "L2",
      "description": "Smaller lunar elliptic semidiurnal constituent",
      "amplitude": 0.07,
      "phase_GMT": 242.0,
      "phase_local": 5.8,
      "speed": 29.528479,
      "comments": "Average of three (3) 29-day harmonic analyses.  Sa, Ssa, and Mf from 9418767 North Spit, Humboldt Bay."
    },
    {
      "number": 34,
      "name": "2MK3",
      "description": "Shallow water terdiurnal constituent",
      "amplitude": 0.0,
      "phase_GMT": 0.0,
      "phase_local": 0.0,
      "speed": 42.92714,
      "comments": "Average of three (3) 29-day harmonic analyses.  Sa, Ssa, and Mf from 9418767 North Spit, Humboldt Bay."
    },
    {
      "number": 35,
      "name": "K2",
      "description": "Lunisolar semidiurnal constituent",
      "amplitude": 0.17,
      "phase_GMT": 245.6,
      "phase_local": 4.9,
      "speed": 30.082138,
      "comments": "Average of three (3) 29-day harmonic analyses.  Sa, Ssa, and Mf from 9418767 North Spit, Humboldt Bay."
    },
    {
      "number": 36,
      "name": "M8",
      "description": "Shallow water eighth diurnal constituent",
      "amplitude": 0.01,
      "phase_GMT": 304.8,
      "phase_local": 97.3,
      "speed": 115.93642,
      "comments": "Average of three (3) 29-day harmonic analyses.  Sa, Ssa, and Mf from 9418767 North Spit, Humboldt Bay."
    },
    {
      "number": 37,
      "name": "MS4",
      "description": "Shallow water quarter diurnal constituent",
      "amplitude": 0.0,
      "phase_GMT": 0.0,
      "phase_local": 0.0,
      "speed": 58.984104,
      "comments": "Average of three (3) 29-day harmonic analyses.  Sa, Ssa, and Mf from 9418767 North Spit, Humboldt Bay."
    }
  ],
  "self": "https://api.tidesandcurrents.noaa.gov/mdapi/prod/webapi/stations/9418817/harcon.json"
}